iex_parser/__init__.py
iex_parser/conversions.py
iex_parser/iex_to_csv.py
iex_parser/iex_to_json.py
iex_parser/messages.py
iex_parser/parser.py
iex_parser-1.7.0.dist-info/entry_points.txt
iex_parser-1.7.0.dist-info/LICENSE
iex_parser-1.7.0.dist-info/WHEEL
iex_parser-1.7.0.dist-info/METADATA
iex_parser-1.7.0.dist-info/RECORD
