Metadata-Version: 2.1
Name: iex-parser
Version: 1.7.0
Summary: Parser for IEX data files
Home-page: https://github.com/rob-blackbourn/iex_parser
License: Apache-2.0
Keywords: iex,parser,pcap
Author: Rob Blackbourn
Author-email: rob.blackbourn@gmail.com
Requires-Python: >=3.7,<4.0
Classifier: License :: OSI Approved :: Apache Software License
Classifier: Programming Language :: Python :: 3
Classifier: Programming Language :: Python :: 3.10
Classifier: Programming Language :: Python :: 3.7
Classifier: Programming Language :: Python :: 3.8
Classifier: Programming Language :: Python :: 3.9
Requires-Dist: scapy (>=2.4,<3.0)
Project-URL: Repository, https://github.com/rob-blackbourn/iex_parser
